.gitignore
MANIFEST.in
README.rst
bootstrap.py
buildout.cfg
setup.py
collective/__init__.py
collective.js.twittertext.egg-info/PKG-INFO
collective.js.twittertext.egg-info/SOURCES.txt
collective.js.twittertext.egg-info/dependency_links.txt
collective.js.twittertext.egg-info/entry_points.txt
collective.js.twittertext.egg-info/namespace_packages.txt
collective.js.twittertext.egg-info/not-zip-safe
collective.js.twittertext.egg-info/requires.txt
collective.js.twittertext.egg-info/top_level.txt
collective/js/__init__.py
collective/js/twittertext/__init__.py
collective/js/twittertext/configure.zcml
collective/js/twittertext/profiles/default/jsregistry.xml
collective/js/twittertext/profiles/default/metadata.xml
collective/js/twittertext/resources/twitter-text.js
docs/HISTORY.txt